pygoat/echo/echo.py
pygoat/main.py
pygoat-0.1.2.dist-info/entry_points.txt
pygoat-0.1.2.dist-info/WHEEL
pygoat-0.1.2.dist-info/METADATA
pygoat-0.1.2.dist-info/RECORD
